{
  "category": "Бытовая химия и гигиена / Личная гигиена / Ватно-бумажная продукция / Полотенца / Zewa",
  "characteristics": {
    "Бренд": "Zewa",
    "Вид бумажных полотенец": "Рулонные",
    "Перфорация": "С перфорацией",
    "Тип": "Бумажные полотенца",
    "Цвет": "Белый"
  },
  "description": "Zewa теперь Zemma. Любимый бренд и высокое качество под новым названием! Мы действительно изменили визуальный облик нашего бренда, однако это никак не повлияло на состав или технологию производства. Наш главный приоритет остается прежним – продолжать предоставлять нашим потребителям товары высокого качества, к которым вы так привыкли и которым доверяете. Бумажные полотенца Zemma - универсальный и незаменимый помощник в доме. С их помощью можно легко вытереть пролитую жидкость, отполировать до блеска стекла или посуду, очистить поверхности. Бумажные полотенца Zemma с дополнительной перфорацией 1/2 листа позволяют экономичнее расходовать продукт и половину листа при небольших загрязнениях. Продукт изготовлен из 100% переработанного волокна, а это значит, что используя такой продукт, вы помогаете рациональному использованию природных ресурсов и вносите свой вклад в усиление экономики замкнутого цикла.",
  "hashtags": [
    "#бумажные",
    "#полотенца",
    "#zewa",
    "#zemma",
    "#листа",
    "#рулона"
  ],
  "product_id": "24962122",
  "rating": 4.9,
  "review_count": 657686,
  "scraped_at": "2026-05-20T22:25:27.813Z",
  "source_url": "https://www.ozon.ru/product/bumazhnye-polotentsa-zewa-zemma-1-2-lista-4-rulona-24962122/",
  "title": "Бумажные полотенца Zewa/Zemma 1/2 листа, 4 рулона",
  "collection_target_category": "Бытовая химия",
  "collection_source_subcategory": null,
  "collection_batch": "tz_200_2026_05_21"
}