{
  "category": "Товары для животных / Для кошек / Корма и лакомства / Сухие корма / Брит",
  "characteristics": {
    "Артикул": "489093975",
    "Бренд": "Брит",
    "Вес товара, г": "2000",
    "Вкус корма для животных": "Лосось, Курица",
    "Возраст животного": "Для взрослых",
    "Единиц в одном товаре": "1",
    "Основной ингредиент": "Рыба",
    "Особые потребности": "Кастрированным и стерилизованным",
    "Предназначено для": "Для кошек",
    "Размер животного": "Малый, Крупный, Средний",
    "Размер упаковки (Длина х Ширина х Высота), см": "370 x 250 x 90",
    "Содержание мяса, субпродуктов, %": "37",
    "Срок годности в днях": "540",
    "Страна-изготовитель": "Россия",
    "Тип": "Корм сухой",
    "Упаковка": "Пакет",
    "Условия хранения": "В прохладном темном месте"
  },
  "description": "Сухой корм Brit Premium с лососем и курицей предназначен для взрослых стерилизованных кошек. Сбалансированный состав содержит все витамины и минералы, необходимые для ежедневного здорового питания вашего питомца. Корм поможет сохранить здоровье и активность вашего питомца, а мясо в составе обеспечивает притягательный аромат и вкус, который не оставит равнодушным даже самых привередливых питомцев.",
  "hashtags": [
    "#корм",
    "#взрослых",
    "#стерилизованных",
    "#кошек",
    "#сухой",
    "#брит",
    "#премиум",
    "#лососем",
    "#курицей"
  ],
  "product_id": "489093975",
  "rating": 4.9,
  "review_count": 51697,
  "scraped_at": "2026-05-20T22:22:53.732Z",
  "source_url": "https://www.ozon.ru/product/korm-dlya-vzroslyh-sterilizovannyh-koshek-suhoy-brit-premium-s-lososem-i-kuritsey-2-kg-489093975/",
  "title": "Корм для взрослых стерилизованных кошек сухой, Брит Премиум с лососем и курицей, 2 кг",
  "collection_target_category": "Товары для животных",
  "collection_source_subcategory": null,
  "collection_batch": "tz_200_2026_05_21"
}