{
  "category": "Красота и здоровье / Уход за лицом / Увлажнение и питание / Кремы / КСЕОС 5.0",
  "characteristics": {
    "Аромат": "нет",
    "Применение": "Дневной уход",
    "Тип": "Крем для ухода за кожей",
    "Тип кожи": "Для проблемной кожи, Для сухой кожи, Для чувствительной кожи",
    "Эффект от использования уходовой косметики": "Восстановление, Увлажнение"
  },
  "description": "КСЕОС pH 5.0 Крем восстанавливающий для лица и тела при повышенной сухости кожи, 150 млКрем насыщенной текстуры, обогащенный липидами, смягчает и увлажняет сухую кожу, способствует восстановлению ее водно-липидного баланса.Рекомендован дерматологами для ежедневного применения при повышенной сухости кожи (ксерозе) и хронических дерматозах: атопический дерматит, псориаз, экзема.Подходит для лица и тела.Без отдушек и красителей.- восстановление защитной функции кожи- эффективное увлажнение- смягчение и питание Наилучший результат ухода за сухой кожей достигатся при использовании вместе со специальным средством очищения Гелем очищающим для лица и тела КСЕОС 5.0 и Эмульсией успокаивющей КСЕОС 5.0 для ухода за лицом и телом.",
  "hashtags": [
    "#ксеос",
    "#крем",
    "#восстанавливающий",
    "#лица",
    "#тела",
    "#повышенной",
    "#сухости",
    "#кожи"
  ],
  "product_id": "695209295",
  "rating": 4.9,
  "review_count": 2731,
  "scraped_at": "2026-05-20T21:09:57.939Z",
  "source_url": "https://www.ozon.ru/product/kseos-ph-5-0-krem-vosstanavlivayushchiy-dlya-litsa-i-tela-pri-povyshennoy-suhosti-kozhi-150-ml-695209295/",
  "title": "КСЕОС pH 5.0 Крем восстанавливающий для лица и тела при повышенной сухости кожи, 150 мл"
}