{
  "url": "https://www.wildberries.ru/catalog/330995368/detail.aspx",
  "nm_id": 330995368,
  "title": "Коврик FLG8.TMMP.040, 80x50 см, пепельно-бежевый",
  "category": "Дом / Ванная / Коврики",
  "source_category": "dom-i-dacha/vannaya/kovriki",
  "brand": "Pragma",
  "description": "Pragma — это бренд эстетичных и функциональных решений для дома, придуманный в Яндекс Фабрике.\n\nОднотонный бежевый коврик Pragma Felgo с ворсом из микрофибры дополнит интерьер ванной комнаты.\nКоврик из полиэстера хорошо впитывает воду и быстро сохнет. Густой, мягкий и высокий ворс — 4,6 см — приятен на ощупь и устойчив к износу. Противоскользящая подложка из термопластичной резины не даёт коврику скользить даже по влажному полу.\n\nРазмер 80 × 50 см подойдёт для большинства ванных комнат. Изделие простое в уходе — его можно постирать в машинке на бережном режиме, следуя знакам на этикетке.\n\nКоврик сочетается с другими предметами коллекции Pragma Felgo — шторами и настольными аксессуарами для ванной комнаты.\n\nГарантия на коврики для ванной комнаты Pragma — 1 год.",
  "characteristics": {
    "Вес с упаковкой (кг)": "1 кг",
    "Ширина упаковки": "11 см",
    "Высота упаковки": "13 см",
    "Длина упаковки": "52 см",
    "Длина предмета": "50 см",
    "Размер коврика": "50х80 см",
    "Форма коврика": "прямоугольная",
    "Материал изделия": "микрофибра",
    "Основа коврика": "резина",
    "Высота ворса": "46 мм",
    "Особенности коврика": "нескользящий; влаговпитывающий",
    "Цвет": "бежевый",
    "Страна производства": "Китай"
  },
  "reviews_count": 40,
  "rating": 4.5,
  "hashtags": []
}
